{"tokenNum": 96, "sentenceNum": 5, "lemmaNum": 69, "lemmaRate": 0.71875, "sentenceLength": 19.2, "allUpperNum": 1, "firstUpperNum": 8, "allUpperRate": 0.010416666666666666, "firstUpperRate": 0.08333333333333333, "declarSentNum": 4, "imperSentNum": 0, "questionNum": 1, "declarSentRate": 0.8, "imperSentRate": 0.0, "questionRate": 0.2, "accent": true, "saturation": 4.928571428571429, "paragraphNum": 0, "nounNum": 14, "verbNum": 11, "adjNum": 7, "infNum": 2, "partPastNum": 0, "partPresNum": 0, "partFutNum": 0, "transNum": 0, "xNum": 4, "advNum": 14, "properNounNum": 2, "numNum": 0, "conjNum": 9, "punctNum": 17, "pronNum": 10, "relPronNum": 1, "demPronNum": 7, "adposNum": 1, "multiplePunctNum": 0, "phraseNum": 0, "nounRate": 0.14583333333333334, "verbRate": 0.11458333333333333, "adjRate": 0.07291666666666667, "infRate": 0.020833333333333332, "partPastRate": 0.0, "partPresRate": 0.0, "partFutRate": 0.0, "transRate": 0.0, "xRate": 0.041666666666666664, "advRate": 0.14583333333333334, "properNounRate": 0.020833333333333332, "numRate": 0.0, "conjRate": 0.09375, "punctRate": 0.17708333333333334, "pronRate": 0.10416666666666667, "relPronRate": 0.010416666666666666, "demPronRate": 0.07291666666666667, "adposRate": 0.010416666666666666, "multiplePunctRate": 0.0, "partsDensityRate": 3.2857142857142856, "contentfulness": 9.2, "phraseRate": 0.0, "pastTenseNum": 1, "presentTenseNum": 8, "condNum": 1, "impNum": 0, "freqNum": 0, "causNum": 0, "modalNum": 1, "sg1VerbNum": 11, "sg2VerbNum": 11, "sg3VerbNum": 11, "pl1VerbNum": 11, "pl2VerbNum": 11, "pl3VerbNum": 11, "superlatNum": 0, "comparatNum": 0, "specDerivSuffixNum": 0, "pluralNounNum": 2, "pastTenseRate": 0.09090909090909091, "presentTenseRate": 0.7272727272727273, "condRate": 0.09090909090909091, "impRate": 0.0, "freqRate": 0.0, "causRate": 0.0, "modalRate": 0.09090909090909091, "sg1VerbRate": 1.0, "sg2VerbRate": 1.0, "sg3VerbRate": 1.0, "pl1VerbRate": 1.0, "pl2VerbRate": 1.0, "pl3VerbRate": 1.0, "superlatRate": 0.0, "comparatRate": 0.0, "specDerivSuffixRate": 0.0, "pluralNounRate": 0.14285714285714285, "subjNum": 3, "objNum": 9, "attNum": 2, "subordNum": 4, "adverbNum": 19, "coordNum": 4, "clauseNum": 14, "simpleNum": 1, "complexNum": 4, "complexity1Num": 2, "complexity2Num": 0, "complexity3Num": 1, "compoundNum": 0, "subjRate": 0.03125, "objRate": 0.09375, "attRate": 0.020833333333333332, "subordRate": 0.041666666666666664, "adverbRate": 0.19791666666666666, "coordRate": 0.041666666666666664, "partsRate": 2.642857142857143, "clauseRate": 2.8, "simpleRate": 0.2, "complexRate": 0.8, "complexity1Rate": 0.4, "complexity2Rate": 0.0, "complexity3Rate": 0.2, "complexClauseRate": 3.25, "sentencesPerParagraph": 0.0, "wordsLengthRate": 5.443037974683544, "compoundRate": 0.0, "positiveNum": 0, "negativeNum": 0, "precoPositiveNum": 0, "precoNegativeNum": 0, "negemoNum": 0, "negationNum": 5, "functionNum": 50, "contentNum": 46, "vulgarNum": 0, "racistNum": 0, "specStyleNum": 0, "addressingNum": 0, "closingNum": 0, "postscriptNum": 0, "brutalNum": 0, "positiveRate": 0.0, "negativeRate": 0.0, "precoPositiveRate": 0.0, "precoNegativeRate": 0.0, "negemoRate": 0.0, "negationRate": 0.052083333333333336, "functionRate": 0.5208333333333334, "contentRate": 0.4791666666666667, "vulgarRate": 0.0, "racistRate": 0.0, "specStyleRate": 0.0, "addressingRate": 0.0, "closingRate": 0.0, "postscriptRate": 0.0, "brutalRate": 0.0, "epistemicNum": 0, "investNum": 0, "conditionNum": 0, "weaselNum": 0, "peacockNum": 0, "hedgeNum": 0, "doxasticNum": 0, "epistemicRate": 0.0, "investRate": 0.0, "conditionRate": 0.0, "weaselRate": 0.0, "peacockRate": 0.0, "hedgeRate": 0.0, "doxasticRate": 0.0, "loveNum": 0, "anxietyNum": 0, "sorrowNum": 0, "joyNum": 0, "disgustNum": 0, "fearNum": 0, "surpriseNum": 0, "angerNum": 0, "loveRate": 0.0, "anxietyRate": 0.0, "sorrowRate": 0.0, "joyRate": 0.0, "disgustRate": 0.0, "fearRate": 0.0, "surpriseRate": 0.0, "angerRate": 0.0, "slangBeGeneralNum": 0, "slangBeCigaretteNum": 0, "slangBeHumanNum": 0, "slangBeVehicleNum": 0, "slangBeDrugNum": 0, "slangBvNum": 0, "slangBeGeneralRate": 0.0, "slangBeCigaretteRate": 0.0, "slangBeHumanRate": 0.0, "slangBeVehicleRate": 0.0, "slangBeDrugRate": 0.0, "slangBvRate": 0.0, "speechactNum": 0, "quoteNum": 0, "dashNum": 0, "publicNum": 0, "privateNum": 0, "suasiveNum": 0, "discMarkerNum": 0, "smileyNum": 0, "dateNum": 0, "hesitationNum": 0, "restartNum": 0, "repeatNum": 0, "conjBeforeDiscNum": 0, "conjAfterDiscNum": 0, "wordBeforeHesitationNum": 0, "wordAfterHesitationNum": 0, "otherCollocationNum": 0, "speechactRate": 0.0, "quoteRate": 0.0, "dashRate": 0.0, "publicRate": 0.0, "privateRate": 0.0, "suasiveRate": 0.0, "discMarkerRate": 0.0, "smileyRate": 0.0, "dateRate": 0.0, "hesitationRate": 0.0, "restartRate": 0.0, "repeatRate": 0.0, "conjBeforeDiscRate": 0.0, "conjAfterDiscRate": 0.0, "wordBeforeHesitationRate": 0.0, "wordAfterHesitationRate": 0.0, "otherCollocationRate": 0.0, "easyWordNum": 92, "hardWordNum": 4, "easyWordRate": 0.9583333333333334, "hardWordRate": 0.041666666666666664, "fleschReadingEaseScore": 63.090750000000014, "gunningFogIndex": 7.696666666666667, "fleschKincaidGradeLevel": 9.22925, "colemanLiauIndex": 11.379739583333329, "smogIndex": 5.2151, "automatedReadabilityIndex": 9.904687500000001, "linsearWriteIndex": 9.0, "author": "", "locationNameNum": 0, "locationNameRate": 0.0, "personNameNum": 1, "personNameRate": 0.010416666666666666, "organizationNameNum": 0, "organizationNameRate": 0.0, "misspelledNum": 3, "misspelledRate": 0.03125, "missingAccentNum": 2, "missingAccentRate": 0.020833333333333332, "foreignAccentNum": 0, "foreignAccentRate": 0.0, "wordConcatNum": 0, "wordConcatRate": 0.0, "jLyMistakeNum": 0, "jLyMistakeRate": 0.0, "publicVNum": 0, "freqSuffixNum": 0, "partsNum": 37, "clauseWordNum": 14, "privateVNum": 0}