{"tokenNum": 106, "sentenceNum": 11, "lemmaNum": 64, "lemmaRate": 0.6037735849056604, "sentenceLength": 9.636363636363637, "allUpperNum": 0, "firstUpperNum": 15, "allUpperRate": 0.0, "firstUpperRate": 0.14150943396226415, "declarSentNum": 10, "imperSentNum": 1, "questionNum": 0, "declarSentRate": 0.9090909090909091, "imperSentRate": 0.09090909090909091, "questionRate": 0.0, "accent": false, "saturation": 4.0, "paragraphNum": 0, "nounNum": 21, "verbNum": 13, "adjNum": 9, "infNum": 1, "partPastNum": 1, "partPresNum": 0, "partFutNum": 0, "transNum": 0, "xNum": 10, "advNum": 7, "properNounNum": 4, "numNum": 0, "conjNum": 3, "punctNum": 24, "pronNum": 6, "relPronNum": 2, "demPronNum": 6, "adposNum": 0, "multiplePunctNum": 2, "phraseNum": 0, "nounRate": 0.19811320754716982, "verbRate": 0.12264150943396226, "adjRate": 0.08490566037735849, "infRate": 0.009433962264150943, "partPastRate": 0.009433962264150943, "partPresRate": 0.0, "partFutRate": 0.0, "transRate": 0.0, "xRate": 0.09433962264150944, "advRate": 0.0660377358490566, "properNounRate": 0.03773584905660377, "numRate": 0.0, "conjRate": 0.02830188679245283, "punctRate": 0.22641509433962265, "pronRate": 0.05660377358490566, "relPronRate": 0.018867924528301886, "demPronRate": 0.05660377358490566, "adposRate": 0.0, "multiplePunctRate": 0.08333333333333333, "partsDensityRate": 3.125, "contentfulness": 4.545454545454546, "phraseRate": 0.0, "pastTenseNum": 3, "presentTenseNum": 9, "condNum": 0, "impNum": 3, "freqNum": 0, "causNum": 0, "modalNum": 0, "sg1VerbNum": 13, "sg2VerbNum": 13, "sg3VerbNum": 13, "pl1VerbNum": 13, "pl2VerbNum": 13, "pl3VerbNum": 13, "superlatNum": 0, "comparatNum": 0, "specDerivSuffixNum": 0, "pluralNounNum": 10, "pastTenseRate": 0.23076923076923078, "presentTenseRate": 0.6923076923076923, "condRate": 0.0, "impRate": 0.23076923076923078, "freqRate": 0.0, "causRate": 0.0, "modalRate": 0.0, "sg1VerbRate": 1.0, "sg2VerbRate": 1.0, "sg3VerbRate": 1.0, "pl1VerbRate": 1.0, "pl2VerbRate": 1.0, "pl3VerbRate": 1.0, "superlatRate": 0.0, "comparatRate": 0.0, "specDerivSuffixRate": 0.0, "pluralNounRate": 0.47619047619047616, "subjNum": 8, "objNum": 4, "attNum": 5, "subordNum": 5, "adverbNum": 9, "coordNum": 4, "clauseNum": 16, "simpleNum": 7, "complexNum": 4, "complexity1Num": 3, "complexity2Num": 1, "complexity3Num": 0, "compoundNum": 0, "subjRate": 0.07547169811320754, "objRate": 0.03773584905660377, "attRate": 0.04716981132075472, "subordRate": 0.04716981132075472, "adverbRate": 0.08490566037735849, "coordRate": 0.03773584905660377, "partsRate": 1.875, "clauseRate": 1.4545454545454546, "simpleRate": 0.6363636363636364, "complexRate": 0.36363636363636365, "complexity1Rate": 0.2727272727272727, "complexity2Rate": 0.09090909090909091, "complexity3Rate": 0.0, "complexClauseRate": 2.25, "sentencesPerParagraph": 0.0, "wordsLengthRate": 5.548780487804878, "compoundRate": 0.0, "positiveNum": 0, "negativeNum": 0, "precoPositiveNum": 0, "precoNegativeNum": 0, "negemoNum": 0, "negationNum": 0, "functionNum": 56, "contentNum": 50, "vulgarNum": 0, "racistNum": 0, "specStyleNum": 0, "addressingNum": 0, "closingNum": 0, "postscriptNum": 0, "brutalNum": 0, "positiveRate": 0.0, "negativeRate": 0.0, "precoPositiveRate": 0.0, "precoNegativeRate": 0.0, "negemoRate": 0.0, "negationRate": 0.0, "functionRate": 0.5283018867924528, "contentRate": 0.4716981132075472, "vulgarRate": 0.0, "racistRate": 0.0, "specStyleRate": 0.0, "addressingRate": 0.0, "closingRate": 0.0, "postscriptRate": 0.0, "brutalRate": 0.0, "epistemicNum": 0, "investNum": 0, "conditionNum": 0, "weaselNum": 0, "peacockNum": 0, "hedgeNum": 0, "doxasticNum": 0, "epistemicRate": 0.0, "investRate": 0.0, "conditionRate": 0.0, "weaselRate": 0.0, "peacockRate": 0.0, "hedgeRate": 0.0, "doxasticRate": 0.0, "loveNum": 0, "anxietyNum": 0, "sorrowNum": 0, "joyNum": 0, "disgustNum": 0, "fearNum": 0, "surpriseNum": 0, "angerNum": 0, "loveRate": 0.0, "anxietyRate": 0.0, "sorrowRate": 0.0, "joyRate": 0.0, "disgustRate": 0.0, "fearRate": 0.0, "surpriseRate": 0.0, "angerRate": 0.0, "slangBeGeneralNum": 0, "slangBeCigaretteNum": 0, "slangBeHumanNum": 0, "slangBeVehicleNum": 0, "slangBeDrugNum": 0, "slangBvNum": 0, "slangBeGeneralRate": 0.0, "slangBeCigaretteRate": 0.0, "slangBeHumanRate": 0.0, "slangBeVehicleRate": 0.0, "slangBeDrugRate": 0.0, "slangBvRate": 0.0, "speechactNum": 0, "quoteNum": 0, "dashNum": 0, "publicNum": 0, "privateNum": 0, "suasiveNum": 0, "discMarkerNum": 0, "smileyNum": 0, "dateNum": 0, "hesitationNum": 0, "restartNum": 0, "repeatNum": 0, "conjBeforeDiscNum": 0, "conjAfterDiscNum": 0, "wordBeforeHesitationNum": 0, "wordAfterHesitationNum": 0, "otherCollocationNum": 0, "speechactRate": 0.0, "quoteRate": 0.0, "dashRate": 0.0, "publicRate": 0.0, "privateRate": 0.0, "suasiveRate": 0.0, "discMarkerRate": 0.0, "smileyRate": 0.0, "dateRate": 0.0, "hesitationRate": 0.0, "restartRate": 0.0, "repeatRate": 0.0, "conjBeforeDiscRate": 0.0, "conjAfterDiscRate": 0.0, "wordBeforeHesitationRate": 0.0, "wordAfterHesitationRate": 0.0, "otherCollocationRate": 0.0, "easyWordNum": 100, "hardWordNum": 6, "easyWordRate": 0.9433962264150944, "hardWordRate": 0.05660377358490566, "fleschReadingEaseScore": 83.72201543739281, "gunningFogIndex": 3.877186963979417, "fleschKincaidGradeLevel": 3.97572898799314, "colemanLiauIndex": 10.426858490566033, "smogIndex": 5.683917801722854, "automatedReadabilityIndex": 4.36101200686106, "linsearWriteIndex": 3.631217838765009, "author": "", "locationNameNum": 0, "locationNameRate": 0.0, "personNameNum": 1, "personNameRate": 0.009433962264150943, "organizationNameNum": 0, "organizationNameRate": 0.0, "misspelledNum": 24, "misspelledRate": 0.22641509433962265, "missingAccentNum": 18, "missingAccentRate": 0.16981132075471697, "foreignAccentNum": 0, "foreignAccentRate": 0.0, "wordConcatNum": 0, "wordConcatRate": 0.0, "jLyMistakeNum": 1, "jLyMistakeRate": 0.009433962264150943, "publicVNum": 0, "freqSuffixNum": 0, "partsNum": 30, "clauseWordNum": 16, "privateVNum": 0}