{"tokenNum": 119, "sentenceNum": 4, "lemmaNum": 67, "lemmaRate": 0.5630252100840336, "sentenceLength": 29.75, "allUpperNum": 0, "firstUpperNum": 5, "allUpperRate": 0.0, "firstUpperRate": 0.04201680672268908, "declarSentNum": 4, "imperSentNum": 0, "questionNum": 0, "declarSentRate": 1.0, "imperSentRate": 0.0, "questionRate": 0.0, "accent": true, "saturation": 8.375, "paragraphNum": 0, "nounNum": 36, "verbNum": 4, "adjNum": 7, "infNum": 0, "partPastNum": 0, "partPresNum": 0, "partFutNum": 0, "transNum": 0, "xNum": 3, "advNum": 2, "properNounNum": 1, "numNum": 1, "conjNum": 4, "punctNum": 41, "pronNum": 2, "relPronNum": 0, "demPronNum": 1, "adposNum": 0, "multiplePunctNum": 1, "phraseNum": 0, "nounRate": 0.3025210084033613, "verbRate": 0.03361344537815126, "adjRate": 0.058823529411764705, "infRate": 0.0, "partPastRate": 0.0, "partPresRate": 0.0, "partFutRate": 0.0, "transRate": 0.0, "xRate": 0.025210084033613446, "advRate": 0.01680672268907563, "properNounRate": 0.008403361344537815, "numRate": 0.008403361344537815, "conjRate": 0.03361344537815126, "punctRate": 0.3445378151260504, "pronRate": 0.01680672268907563, "relPronRate": 0.0, "demPronRate": 0.008403361344537815, "adposRate": 0.0, "multiplePunctRate": 0.024390243902439025, "partsDensityRate": 6.125, "contentfulness": 12.25, "phraseRate": 0.0, "pastTenseNum": 0, "presentTenseNum": 4, "condNum": 0, "impNum": 0, "freqNum": 0, "causNum": 0, "modalNum": 0, "sg1VerbNum": 4, "sg2VerbNum": 4, "sg3VerbNum": 4, "pl1VerbNum": 4, "pl2VerbNum": 4, "pl3VerbNum": 4, "superlatNum": 0, "comparatNum": 0, "specDerivSuffixNum": 0, "pluralNounNum": 10, "pastTenseRate": 0.0, "presentTenseRate": 1.0, "condRate": 0.0, "impRate": 0.0, "freqRate": 0.0, "causRate": 0.0, "modalRate": 0.0, "sg1VerbRate": 1.0, "sg2VerbRate": 1.0, "sg3VerbRate": 1.0, "pl1VerbRate": 1.0, "pl2VerbRate": 1.0, "pl3VerbRate": 1.0, "superlatRate": 0.0, "comparatRate": 0.0, "specDerivSuffixRate": 0.0, "pluralNounRate": 0.2777777777777778, "subjNum": 2, "objNum": 1, "attNum": 5, "subordNum": 2, "adverbNum": 4, "coordNum": 29, "clauseNum": 8, "simpleNum": 2, "complexNum": 2, "complexity1Num": 0, "complexity2Num": 2, "complexity3Num": 0, "compoundNum": 0, "subjRate": 0.01680672268907563, "objRate": 0.008403361344537815, "attRate": 0.04201680672268908, "subordRate": 0.01680672268907563, "adverbRate": 0.03361344537815126, "coordRate": 0.24369747899159663, "partsRate": 5.125, "clauseRate": 2.0, "simpleRate": 0.5, "complexRate": 0.5, "complexity1Rate": 0.0, "complexity2Rate": 0.5, "complexity3Rate": 0.0, "complexClauseRate": 3.0, "sentencesPerParagraph": 0.0, "wordsLengthRate": 5.884615384615385, "compoundRate": 0.0, "positiveNum": 0, "negativeNum": 0, "precoPositiveNum": 0, "precoNegativeNum": 0, "negemoNum": 0, "negationNum": 0, "functionNum": 70, "contentNum": 49, "vulgarNum": 0, "racistNum": 0, "specStyleNum": 0, "addressingNum": 0, "closingNum": 0, "postscriptNum": 0, "brutalNum": 0, "positiveRate": 0.0, "negativeRate": 0.0, "precoPositiveRate": 0.0, "precoNegativeRate": 0.0, "negemoRate": 0.0, "negationRate": 0.0, "functionRate": 0.5882352941176471, "contentRate": 0.4117647058823529, "vulgarRate": 0.0, "racistRate": 0.0, "specStyleRate": 0.0, "addressingRate": 0.0, "closingRate": 0.0, "postscriptRate": 0.0, "brutalRate": 0.0, "epistemicNum": 0, "investNum": 0, "conditionNum": 0, "weaselNum": 0, "peacockNum": 0, "hedgeNum": 0, "doxasticNum": 0, "epistemicRate": 0.0, "investRate": 0.0, "conditionRate": 0.0, "weaselRate": 0.0, "peacockRate": 0.0, "hedgeRate": 0.0, "doxasticRate": 0.0, "loveNum": 0, "anxietyNum": 0, "sorrowNum": 0, "joyNum": 0, "disgustNum": 0, "fearNum": 0, "surpriseNum": 0, "angerNum": 0, "loveRate": 0.0, "anxietyRate": 0.0, "sorrowRate": 0.0, "joyRate": 0.0, "disgustRate": 0.0, "fearRate": 0.0, "surpriseRate": 0.0, "angerRate": 0.0, "slangBeGeneralNum": 0, "slangBeCigaretteNum": 0, "slangBeHumanNum": 0, "slangBeVehicleNum": 0, "slangBeDrugNum": 0, "slangBvNum": 0, "slangBeGeneralRate": 0.0, "slangBeCigaretteRate": 0.0, "slangBeHumanRate": 0.0, "slangBeVehicleRate": 0.0, "slangBeDrugRate": 0.0, "slangBvRate": 0.0, "speechactNum": 0, "quoteNum": 0, "dashNum": 0, "publicNum": 0, "privateNum": 0, "suasiveNum": 0, "discMarkerNum": 0, "smileyNum": 0, "dateNum": 0, "hesitationNum": 0, "restartNum": 0, "repeatNum": 0, "conjBeforeDiscNum": 0, "conjAfterDiscNum": 0, "wordBeforeHesitationNum": 0, "wordAfterHesitationNum": 0, "otherCollocationNum": 0, "speechactRate": 0.0, "quoteRate": 0.0, "dashRate": 0.0, "publicRate": 0.0, "privateRate": 0.0, "suasiveRate": 0.0, "discMarkerRate": 0.0, "smileyRate": 0.0, "dateRate": 0.0, "hesitationRate": 0.0, "restartRate": 0.0, "repeatRate": 0.0, "conjBeforeDiscRate": 0.0, "conjAfterDiscRate": 0.0, "wordBeforeHesitationRate": 0.0, "wordAfterHesitationRate": 0.0, "otherCollocationRate": 0.0, "easyWordNum": 108, "hardWordNum": 11, "easyWordRate": 0.907563025210084, "hardWordRate": 0.09243697478991597, "fleschReadingEaseScore": 64.31269957983196, "gunningFogIndex": 11.936974789915967, "fleschKincaidGradeLevel": 11.679726890756303, "colemanLiauIndex": 8.799310924369749, "smogIndex": 6.588339656340683, "automatedReadabilityIndex": 13.116176470588236, "linsearWriteIndex": 14.495798319327731, "author": "", "locationNameNum": 0, "locationNameRate": 0.0, "personNameNum": 0, "personNameRate": 0.0, "organizationNameNum": 0, "organizationNameRate": 0.0, "misspelledNum": 3, "misspelledRate": 0.025210084033613446, "missingAccentNum": 0, "missingAccentRate": 0.0, "foreignAccentNum": 0, "foreignAccentRate": 0.0, "wordConcatNum": 1, "wordConcatRate": 0.008403361344537815, "jLyMistakeNum": 0, "jLyMistakeRate": 0.0, "publicVNum": 0, "freqSuffixNum": 0, "partsNum": 41, "clauseWordNum": 8, "privateVNum": 0}